MANIFEST.in
README.md
package.json
pyproject.toml
setup.cfg
setup.py
dist/CMakeLists.txt
dist/LICENSE
dist/cmake/Pybind.txt.in
dist/cmake/arrow.txt.in
dist/cmake/date.txt.in
dist/cmake/double-conversion.txt.in
dist/cmake/exprtk.txt.in
dist/cmake/flatbuffers.txt.in
dist/cmake/hopscotch.txt.in
dist/cmake/lz4.txt.in
dist/cmake/ordered-map.txt.in
dist/cmake/rapidjson.txt.in
dist/cmake/re2.txt.in
dist/cmake/arrow/CMakeLists.txt
dist/cmake/arrow/config.h
dist/cmake/modules/FindColor.cmake
dist/cmake/modules/FindExprTk.cmake
dist/cmake/modules/FindFlatbuffers.cmake
dist/cmake/modules/FindInstallDependency.cmake
dist/cmake/modules/FindNumPy.cmake
dist/cmake/modules/FindPybind.cmake
dist/cmake/modules/FindPythonHeaders.cmake
dist/cmake/modules/FindRe2.cmake
dist/cmake/re2/CMakeLists.txt
dist/src/cpp/aggregate.cpp
dist/src/cpp/aggspec.cpp
dist/src/cpp/arg_sort.cpp
dist/src/cpp/arrow_csv.cpp
dist/src/cpp/arrow_format.cpp
dist/src/cpp/arrow_loader.cpp
dist/src/cpp/arrow_writer.cpp
dist/src/cpp/base.cpp
dist/src/cpp/base_impl_linux.cpp
dist/src/cpp/base_impl_osx.cpp
dist/src/cpp/base_impl_wasm.cpp
dist/src/cpp/base_impl_win.cpp
dist/src/cpp/binding.cpp
dist/src/cpp/column.cpp
dist/src/cpp/comparators.cpp
dist/src/cpp/compat.cpp
dist/src/cpp/compat_impl_linux.cpp
dist/src/cpp/compat_impl_osx.cpp
dist/src/cpp/compat_impl_wasm.cpp
dist/src/cpp/compat_impl_win.cpp
dist/src/cpp/computed_expression.cpp
dist/src/cpp/computed_function.cpp
dist/src/cpp/config.cpp
dist/src/cpp/context_base.cpp
dist/src/cpp/context_grouped_pkey.cpp
dist/src/cpp/context_handle.cpp
dist/src/cpp/context_iterators.cpp
dist/src/cpp/context_one.cpp
dist/src/cpp/context_two.cpp
dist/src/cpp/context_unit.cpp
dist/src/cpp/context_zero.cpp
dist/src/cpp/data.cpp
dist/src/cpp/data_slice.cpp
dist/src/cpp/data_table.cpp
dist/src/cpp/date.cpp
dist/src/cpp/date_parser.cpp
dist/src/cpp/dense_nodes.cpp
dist/src/cpp/dense_tree.cpp
dist/src/cpp/dense_tree_context.cpp
dist/src/cpp/dependency.cpp
dist/src/cpp/emscripten.cpp
perspect.egg-info/PKG-INFO
perspect.egg-info/SOURCES.txt
perspect.egg-info/dependency_links.txt
perspect.egg-info/not-zip-safe
perspect.egg-info/requires.txt
perspect.egg-info/top_level.txt
