Metadata-Version: 2.1
Name: perspect
Version: 2.6.1
Summary: Python bindings and JupyterLab integration for Perspective
Home-page: https://github.com/finos/perspective
Author: Perspective Authors
Author-email: info@finos.org
License: Apache 2.0
Keywords: analytics tools plotting
Classifier: Development Status :: 5 - Production/Stable
Classifier: Programming Language :: Python :: 3
Classifier: Programming Language :: Python :: 3.7
Classifier: Programming Language :: Python :: 3.8
Classifier: Programming Language :: Python :: 3.9
Classifier: Programming Language :: Python :: 3.10
Classifier: Programming Language :: Python :: 3.11
Classifier: Framework :: Jupyter :: JupyterLab
Classifier: Framework :: Jupyter :: JupyterLab :: 3
Classifier: Framework :: Jupyter :: JupyterLab :: Extensions
Classifier: Framework :: Jupyter :: JupyterLab :: Extensions :: Mime Renderers
Classifier: Framework :: Jupyter :: JupyterLab :: Extensions :: Prebuilt
Requires-Python: >=3.7
Requires-Dist: ipywidgets<9,>=7.5.1
Requires-Dist: future<1,>=0.16.0
Requires-Dist: numpy<2,>=1.21.6
Requires-Dist: pandas<3,>=0.22.0
Requires-Dist: python-dateutil<3,>=2.8.0
Requires-Dist: traitlets<6,>=4.3.2
Provides-Extra: aiohttp
Requires-Dist: aiohttp<4,>=3; extra == "aiohttp"
Provides-Extra: dev
Requires-Dist: black==23.1.0; extra == "dev"
Requires-Dist: Faker>=1.0.0; extra == "dev"
Requires-Dist: flake8>=5; extra == "dev"
Requires-Dist: flake8-black>=0.3.3; extra == "dev"
Requires-Dist: httpx<1,>=0.23; extra == "dev"
Requires-Dist: jupyter_packaging==0.12.3; extra == "dev"
Requires-Dist: pip; extra == "dev"
Requires-Dist: psutil<6,>=5; extra == "dev"
Requires-Dist: pybind11<3,>=2.4.0; extra == "dev"
Requires-Dist: pyarrow>=0.16.0; extra == "dev"
Requires-Dist: pytest>=4.3.0; extra == "dev"
Requires-Dist: pytest-aiohttp>=1; extra == "dev"
Requires-Dist: pytest-asyncio>=0.20; extra == "dev"
Requires-Dist: pytest-cov>=3; extra == "dev"
Requires-Dist: pytest-check-links>=0.7; extra == "dev"
Requires-Dist: pytest-tornado>=0.8; extra == "dev"
Requires-Dist: pytz>=2022; extra == "dev"
Requires-Dist: Sphinx>=1.8.4; extra == "dev"
Requires-Dist: sphinx-markdown-builder>=0.5.2; extra == "dev"
Requires-Dist: wheel; extra == "dev"
Requires-Dist: ipywidgets<9,>=7.5.1; extra == "dev"
Requires-Dist: future<1,>=0.16.0; extra == "dev"
Requires-Dist: numpy<2,>=1.21.6; extra == "dev"
Requires-Dist: pandas<3,>=0.22.0; extra == "dev"
Requires-Dist: python-dateutil<3,>=2.8.0; extra == "dev"
Requires-Dist: traitlets<6,>=4.3.2; extra == "dev"
Requires-Dist: aiohttp<4,>=3; extra == "dev"
Requires-Dist: jupyterlab<4,>=3.2; extra == "dev"
Requires-Dist: fastapi<1,>=0.70; extra == "dev"
Requires-Dist: starlette<1,>=0.20; extra == "dev"
Requires-Dist: tornado<7,>=4.5.3; extra == "dev"
Provides-Extra: develop
Requires-Dist: black==23.1.0; extra == "develop"
Requires-Dist: Faker>=1.0.0; extra == "develop"
Requires-Dist: flake8>=5; extra == "develop"
Requires-Dist: flake8-black>=0.3.3; extra == "develop"
Requires-Dist: httpx<1,>=0.23; extra == "develop"
Requires-Dist: jupyter_packaging==0.12.3; extra == "develop"
Requires-Dist: pip; extra == "develop"
Requires-Dist: psutil<6,>=5; extra == "develop"
Requires-Dist: pybind11<3,>=2.4.0; extra == "develop"
Requires-Dist: pyarrow>=0.16.0; extra == "develop"
Requires-Dist: pytest>=4.3.0; extra == "develop"
Requires-Dist: pytest-aiohttp>=1; extra == "develop"
Requires-Dist: pytest-asyncio>=0.20; extra == "develop"
Requires-Dist: pytest-cov>=3; extra == "develop"
Requires-Dist: pytest-check-links>=0.7; extra == "develop"
Requires-Dist: pytest-tornado>=0.8; extra == "develop"
Requires-Dist: pytz>=2022; extra == "develop"
Requires-Dist: Sphinx>=1.8.4; extra == "develop"
Requires-Dist: sphinx-markdown-builder>=0.5.2; extra == "develop"
Requires-Dist: wheel; extra == "develop"
Requires-Dist: ipywidgets<9,>=7.5.1; extra == "develop"
Requires-Dist: future<1,>=0.16.0; extra == "develop"
Requires-Dist: numpy<2,>=1.21.6; extra == "develop"
Requires-Dist: pandas<3,>=0.22.0; extra == "develop"
Requires-Dist: python-dateutil<3,>=2.8.0; extra == "develop"
Requires-Dist: traitlets<6,>=4.3.2; extra == "develop"
Requires-Dist: aiohttp<4,>=3; extra == "develop"
Requires-Dist: jupyterlab<4,>=3.2; extra == "develop"
Requires-Dist: fastapi<1,>=0.70; extra == "develop"
Requires-Dist: starlette<1,>=0.20; extra == "develop"
Requires-Dist: tornado<7,>=4.5.3; extra == "develop"
Provides-Extra: fastapi
Requires-Dist: fastapi<1,>=0.70; extra == "fastapi"
Requires-Dist: starlette<1,>=0.20; extra == "fastapi"
Provides-Extra: jupyter
Requires-Dist: jupyterlab<4,>=3.2; extra == "jupyter"
Provides-Extra: starlette
Requires-Dist: fastapi<1,>=0.70; extra == "starlette"
Requires-Dist: starlette<1,>=0.20; extra == "starlette"
Provides-Extra: tornado
Requires-Dist: tornado<7,>=4.5.3; extra == "tornado"
